{
    "bridge": {
        "name": "Homebridge",
        "username": "0E:12:3A:B4:C5:D6",
        "port": 51826,
        "pin": "031-45-154"
    },
    "accessories": [],
    "platforms": [
        {
            "platform": "SwitchbotBLE",
            "name": "SwitchBot",
            "debug": true,
            "_bridge": {
                "username": "0E:29:C4:07:CA:B1",
                "port": 52811
            },
            "devices": [
                {
                    "name": "SwitchBot",
                    "deviceId": "DD:0B:72:15:C3:39",
                    "mode": "switch",
                    "autoOff": false,
                    "autoOffDelay": 1
                }
            ]
        },
        {
            "platform": "config",
            "name": "Config",
            "port": 8581,
            "sudo": true
        }
    ]
}